.gitattributes
.gitignore
.prospector.yaml
.pylintrc
MANIFEST.in
README.rst
requirements.in
requirements.txt
setup.cfg
setup.py
versioneer.py
coneyeye/__init__.py
coneyeye/_version.py
coneyeye/flattendict.py
coneyeye/main.py
coneyeye/mqreport.py
coneyeye.egg-info/PKG-INFO
coneyeye.egg-info/SOURCES.txt
coneyeye.egg-info/dependency_links.txt
coneyeye.egg-info/entry_points.txt
coneyeye.egg-info/not-zip-safe
coneyeye.egg-info/pbr.json
coneyeye.egg-info/requires.txt
coneyeye.egg-info/top_level.txt
coneyeye/_cfgtool/coneyeye
coneyeye/_cfgtool/coneyeye.conf.templ
coneyeye/_cfgtool/install
coneyeye/_cfgtool/logging.conf.templ