Metadata-Version: 1.0
Name: coneyeye
Version: 0.1.post21
Summary: Daemon to map RabbitMQ stats into StatsD
Home-page: https://github.com/clearclaw/coneyeye
Author: J C Lawrence
Author-email: claw@kanga.nu
License: GPL v3.0
Keywords: RabbitMQ,StatsD,daemon
Platform: UNKNOWN
